pynentry.py
pynentry-0.1.7.dist-info/LICENSE
pynentry-0.1.7.dist-info/METADATA
pynentry-0.1.7.dist-info/WHEEL
pynentry-0.1.7.dist-info/top_level.txt
pynentry-0.1.7.dist-info/RECORD
