Metadata-Version: 2.1
Name: pynentry
Version: 0.1.7
Summary: A pythonic wrapper around pinentry for secure password input
Home-page: https://github.com/Laharah/pynentry
Author: laharah
Author-email: laharah22+pyn@gmail.com
License: MIT
Classifier: License :: OSI Approved :: MIT License
Classifier: Programming Language :: Python :: 3 :: Only
Classifier: Programming Language :: Python :: 3.7
Classifier: Development Status :: 5 - Production/Stable
Classifier: Environment :: Console
Classifier: Intended Audience :: Developers
Classifier: Intended Audience :: System Administrators
Classifier: Topic :: Security
Classifier: Topic :: Software Development :: User Interfaces
License-File: LICENSE
